iss/__init__.py
iss/__main__.py
iss/abundance.py
iss/app.py
iss/bam.py
iss/download.py
iss/generator.py
iss/modeller.py
iss/util.py
iss/version.py
iss/error_models/__init__.py
iss/error_models/basic.py
iss/error_models/kde.py
iss/error_models/perfect.py
iss/profiles/HiSeq
iss/profiles/MiSeq
iss/profiles/NovaSeq
iss/profiles/miSeq_0.npz
iss/profiles/miSeq_20.npz
iss/profiles/miSeq_24.npz
iss/profiles/miSeq_28.npz
iss/profiles/miSeq_32.npz
iss/profiles/miSeq_36.npz
iss/profiles/nextSeq.npz
iss/test/__init__.py
iss/test/test_abundance.py
iss/test/test_bam.py
iss/test/test_download.py
iss/test/test_error_model.py
iss/test/test_generator.py
iss/test/test_modeller.py
iss/test/test_util.py
InSilicoSeq-2.0.1.dist-info/LICENSE
InSilicoSeq-2.0.1.dist-info/METADATA
InSilicoSeq-2.0.1.dist-info/WHEEL
InSilicoSeq-2.0.1.dist-info/entry_points.txt
InSilicoSeq-2.0.1.dist-info/top_level.txt
InSilicoSeq-2.0.1.dist-info/RECORD
