Metadata-Version: 2.1
Name: InSilicoSeq
Version: 2.0.1
Summary: a sequencing simulator
Home-page: https://github.com/HadrienG/InSilicoSeq
Download-URL: https://github.com/HadrienG/InSilicoSeq/tarball/2.0.1
Author: Hadrien Gourlé
Author-email: hadrien.gourle@slu.se
License: MIT
License-File: LICENSE
Requires-Dist: numpy
Requires-Dist: scipy
Requires-Dist: biopython (>=1.79)
Requires-Dist: pysam (>=0.15.1)
Requires-Dist: requests
